odoo10_addon_currency_rate_update-10.0.1.0.0.99.dev30-py3.8-nspkg.pth
odoo/addons/currency_rate_update/README.rst
odoo/addons/currency_rate_update/__init__.py
odoo/addons/currency_rate_update/__manifest__.py
odoo/addons/currency_rate_update/data/cron.xml
odoo/addons/currency_rate_update/i18n/am.po
odoo/addons/currency_rate_update/i18n/ar.po
odoo/addons/currency_rate_update/i18n/bg.po
odoo/addons/currency_rate_update/i18n/bs.po
odoo/addons/currency_rate_update/i18n/ca.po
odoo/addons/currency_rate_update/i18n/ca_ES.po
odoo/addons/currency_rate_update/i18n/cs.po
odoo/addons/currency_rate_update/i18n/currency_rate_update.pot
odoo/addons/currency_rate_update/i18n/da.po
odoo/addons/currency_rate_update/i18n/de.po
odoo/addons/currency_rate_update/i18n/el_GR.po
odoo/addons/currency_rate_update/i18n/en_GB.po
odoo/addons/currency_rate_update/i18n/es.po
odoo/addons/currency_rate_update/i18n/es_AR.po
odoo/addons/currency_rate_update/i18n/es_CL.po
odoo/addons/currency_rate_update/i18n/es_CO.po
odoo/addons/currency_rate_update/i18n/es_CR.po
odoo/addons/currency_rate_update/i18n/es_DO.po
odoo/addons/currency_rate_update/i18n/es_EC.po
odoo/addons/currency_rate_update/i18n/es_ES.po
odoo/addons/currency_rate_update/i18n/es_MX.po
odoo/addons/currency_rate_update/i18n/es_PE.po
odoo/addons/currency_rate_update/i18n/es_PY.po
odoo/addons/currency_rate_update/i18n/es_VE.po
odoo/addons/currency_rate_update/i18n/et.po
odoo/addons/currency_rate_update/i18n/eu.po
odoo/addons/currency_rate_update/i18n/fa.po
odoo/addons/currency_rate_update/i18n/fi.po
odoo/addons/currency_rate_update/i18n/fr.po
odoo/addons/currency_rate_update/i18n/fr_CA.po
odoo/addons/currency_rate_update/i18n/fr_CH.po
odoo/addons/currency_rate_update/i18n/gl.po
odoo/addons/currency_rate_update/i18n/gl_ES.po
odoo/addons/currency_rate_update/i18n/gu.po
odoo/addons/currency_rate_update/i18n/he.po
odoo/addons/currency_rate_update/i18n/hr.po
odoo/addons/currency_rate_update/i18n/hr_HR.po
odoo/addons/currency_rate_update/i18n/hu.po
odoo10_addon_currency_rate_update-10.0.1.0.0.99.dev30.dist-info/METADATA
odoo10_addon_currency_rate_update-10.0.1.0.0.99.dev30.dist-info/WHEEL
odoo10_addon_currency_rate_update-10.0.1.0.0.99.dev30.dist-info/namespace_packages.txt
odoo10_addon_currency_rate_update-10.0.1.0.0.99.dev30.dist-info/top_level.txt
odoo10_addon_currency_rate_update-10.0.1.0.0.99.dev30.dist-info/RECORD
